[
  {
    "benchmark": "karatsuba",
    "n": 16777216,
    "TASKPARTS_NUM_WORKERS": 64,
    "LD_PRELOAD": "/nix/store/ck10jnbska7d3im30v5mdbnlrgmhai0b-jemalloc-5.3.0/lib/libjemalloc.so",
    "exectime": 0.216,
    "usertime": 13.118,
    "systime": 0.418,
    "nvcsw": 2547,
    "nivcsw": 38,
    "maxrss": 310272,
    "nsignals": 0,
    "nb_vertices": 2251814,
    "nb_steals": 30603,
    "nb_suspends": 0,
    "nb_surplus_transitions": 0,
    "total_work_time": 12.952,
    "total_idle_time": 0.777,
    "total_suspend_time": 0.0,
    "total_time": 13.799,
    "utilization": 0.944,
    "timestamp": "23-11-06 20:39:21.501555"
  },
  {
    "benchmark": "filter_kruskal",
    "TASKPARTS_NUM_WORKERS": 64,
    "LD_PRELOAD": "/nix/store/ck10jnbska7d3im30v5mdbnlrgmhai0b-jemalloc-5.3.0/lib/libjemalloc.so",
    "exectime": 0.006,
    "usertime": 0.312,
    "systime": 0.004,
    "nvcsw": 141,
    "nivcsw": 1,
    "maxrss": 45056,
    "nsignals": 0,
    "nb_vertices": 129,
    "nb_steals": 63,
    "nb_suspends": 0,
    "nb_surplus_transitions": 0,
    "total_work_time": 0.127,
    "total_idle_time": 0.176,
    "total_suspend_time": 0.0,
    "total_time": 0.388,
    "utilization": 0.547,
    "timestamp": "23-11-06 20:39:21.531123"
  },
  {
    "benchmark": "spanning_tree",
    "n": 8388608,
    "TASKPARTS_NUM_WORKERS": 64,
    "LD_PRELOAD": "/nix/store/ck10jnbska7d3im30v5mdbnlrgmhai0b-jemalloc-5.3.0/lib/libjemalloc.so",
    "exectime": 7.57,
    "usertime": 443.9,
    "systime": 39.215,
    "nvcsw": 18643,
    "nivcsw": 825,
    "maxrss": 15838208,
    "nsignals": 0,
    "nb_vertices": 25134637,
    "nb_steals": 34570,
    "nb_suspends": 0,
    "nb_surplus_transitions": 0,
    "total_work_time": 435.666,
    "total_idle_time": 48.055,
    "total_suspend_time": 0.0,
    "total_time": 484.466,
    "utilization": 0.901,
    "timestamp": "23-11-06 20:39:29.152062"
  },
  {
    "benchmark": "push_relabel_max_flow",
    "filename": "../../infiles/com_orkut_sym.adj",
    "TASKPARTS_NUM_WORKERS": 64,
    "LD_PRELOAD": "/nix/store/ck10jnbska7d3im30v5mdbnlrgmhai0b-jemalloc-5.3.0/lib/libjemalloc.so",
    "exectime": 14.952,
    "usertime": 856.792,
    "systime": 95.331,
    "nvcsw": 215435,
    "nivcsw": 1816,
    "maxrss": 32147456,
    "nsignals": 0,
    "nb_vertices": 231097917,
    "nb_steals": 5227143,
    "nb_suspends": 0,
    "nb_surplus_transitions": 0,
    "total_work_time": 797.499,
    "total_idle_time": 157.92,
    "total_suspend_time": 0.0,
    "total_time": 956.944,
    "utilization": 0.835,
    "timestamp": "23-11-06 20:39:44.547634"
  },
  {
    "benchmark": "bucketed_dijkstra",
    "filename": "../../infiles/com_orkut_sym.adj",
    "TASKPARTS_NUM_WORKERS": 64,
    "LD_PRELOAD": "/nix/store/ck10jnbska7d3im30v5mdbnlrgmhai0b-jemalloc-5.3.0/lib/libjemalloc.so",
    "exectime": 1.65,
    "usertime": 64.489,
    "systime": 37.635,
    "nvcsw": 189774,
    "nivcsw": 502,
    "maxrss": 10178560,
    "nsignals": 0,
    "nb_vertices": 3589623,
    "nb_steals": 161475,
    "nb_suspends": 0,
    "nb_surplus_transitions": 0,
    "total_work_time": 75.328,
    "total_idle_time": 29.789,
    "total_suspend_time": 0.0,
    "total_time": 105.616,
    "utilization": 0.718,
    "timestamp": "23-11-06 20:39:46.291286"
  },
  {
    "benchmark": "delaunay",
    "n": 524288,
    "TASKPARTS_NUM_WORKERS": 64,
    "LD_PRELOAD": "/nix/store/ck10jnbska7d3im30v5mdbnlrgmhai0b-jemalloc-5.3.0/lib/libjemalloc.so",
    "exectime": 0.761,
    "usertime": 46.755,
    "systime": 1.319,
    "nvcsw": 9475,
    "nivcsw": 124,
    "maxrss": 921600,
    "nsignals": 0,
    "nb_vertices": 68678671,
    "nb_steals": 181792,
    "nb_suspends": 0,
    "nb_surplus_transitions": 0,
    "total_work_time": 47.091,
    "total_idle_time": 1.504,
    "total_suspend_time": 0.0,
    "total_time": 48.694,
    "utilization": 0.969,
    "timestamp": "23-11-06 20:39:47.089528"
  },
  {
    "benchmark": "rabin_karp",
    "search_string": "xxx",
    "textfilename": "../../infiles/wikisamp.xml",
    "TASKPARTS_NUM_WORKERS": 64,
    "LD_PRELOAD": "/nix/store/ck10jnbska7d3im30v5mdbnlrgmhai0b-jemalloc-5.3.0/lib/libjemalloc.so",
    "exectime": 0.303,
    "usertime": 16.876,
    "systime": 2.036,
    "nvcsw": 768,
    "nivcsw": 72,
    "maxrss": 909312,
    "nsignals": 0,
    "nb_vertices": 5861520,
    "nb_steals": 31159,
    "nb_suspends": 0,
    "nb_surplus_transitions": 0,
    "total_work_time": 11.986,
    "total_idle_time": 7.2,
    "total_suspend_time": 0.0,
    "total_time": 19.363,
    "utilization": 0.628,
    "timestamp": "23-11-06 20:39:47.417582"
  },
  {
    "benchmark": "kruskal",
    "TASKPARTS_NUM_WORKERS": 64,
    "LD_PRELOAD": "/nix/store/ck10jnbska7d3im30v5mdbnlrgmhai0b-jemalloc-5.3.0/lib/libjemalloc.so",
    "exectime": 0.006,
    "usertime": 0.285,
    "systime": 0.0,
    "nvcsw": 31,
    "nivcsw": 1,
    "maxrss": 45056,
    "nsignals": 0,
    "nb_vertices": 129,
    "nb_steals": 63,
    "nb_suspends": 0,
    "nb_surplus_transitions": 0,
    "total_work_time": 0.125,
    "total_idle_time": 0.175,
    "total_suspend_time": 0.0,
    "total_time": 0.362,
    "utilization": 0.517,
    "timestamp": "23-11-06 20:39:47.446772"
  },
  {
    "benchmark": "tokens",
    "filename": "../../infiles/wikisamp.xml",
    "TASKPARTS_NUM_WORKERS": 64,
    "LD_PRELOAD": "/nix/store/ck10jnbska7d3im30v5mdbnlrgmhai0b-jemalloc-5.3.0/lib/libjemalloc.so",
    "exectime": 0.09,
    "usertime": 4.721,
    "systime": 0.384,
    "nvcsw": 3943,
    "nivcsw": 82,
    "maxrss": 356352,
    "nsignals": 0,
    "nb_vertices": 67102,
    "nb_steals": 3455,
    "nb_suspends": 0,
    "nb_surplus_transitions": 0,
    "total_work_time": 1.413,
    "total_idle_time": 4.196,
    "total_suspend_time": 0.0,
    "total_time": 5.734,
    "utilization": 0.268,
    "timestamp": "23-11-06 20:39:47.560013"
  },
  {
    "benchmark": "samplesort",
    "n": 67108864,
    "TASKPARTS_NUM_WORKERS": 64,
    "LD_PRELOAD": "/nix/store/ck10jnbska7d3im30v5mdbnlrgmhai0b-jemalloc-5.3.0/lib/libjemalloc.so",
    "exectime": 0.653,
    "usertime": 32.774,
    "systime": 8.007,
    "nvcsw": 7709,
    "nivcsw": 111,
    "maxrss": 1996800,
    "nsignals": 0,
    "nb_vertices": 6203063,
    "nb_steals": 22391,
    "nb_suspends": 0,
    "nb_surplus_transitions": 0,
    "total_work_time": 34.974,
    "total_idle_time": 6.641,
    "total_suspend_time": 0.0,
    "total_time": 41.779,
    "utilization": 0.841,
    "timestamp": "23-11-06 20:39:48.243994"
  },
  {
    "benchmark": "kmeans_pp",
    "n": 65536,
    "TASKPARTS_NUM_WORKERS": 64,
    "LD_PRELOAD": "/nix/store/ck10jnbska7d3im30v5mdbnlrgmhai0b-jemalloc-5.3.0/lib/libjemalloc.so",
    "exectime": 0.125,
    "usertime": 7.747,
    "systime": 0.032,
    "nvcsw": 1136,
    "nivcsw": 34,
    "maxrss": 105472,
    "nsignals": 0,
    "nb_vertices": 2578994,
    "nb_steals": 110223,
    "nb_suspends": 0,
    "nb_surplus_transitions": 0,
    "total_work_time": 6.071,
    "total_idle_time": 1.812,
    "total_suspend_time": 0.0,
    "total_time": 7.992,
    "utilization": 0.773,
    "timestamp": "23-11-06 20:39:48.393333"
  },
  {
    "benchmark": "scan",
    "n": 1073741824,
    "TASKPARTS_NUM_WORKERS": 64,
    "LD_PRELOAD": "/nix/store/ck10jnbska7d3im30v5mdbnlrgmhai0b-jemalloc-5.3.0/lib/libjemalloc.so",
    "exectime": 2.676,
    "usertime": 99.813,
    "systime": 70.797,
    "nvcsw": 5587,
    "nivcsw": 338,
    "maxrss": 25442304,
    "nsignals": 0,
    "nb_vertices": 3794710,
    "nb_steals": 16754,
    "nb_suspends": 0,
    "nb_surplus_transitions": 0,
    "total_work_time": 111.88,
    "total_idle_time": 58.422,
    "total_suspend_time": 0.0,
    "total_time": 171.289,
    "utilization": 0.659,
    "timestamp": "23-11-06 20:39:51.103728"
  },
  {
    "benchmark": "kcore",
    "filename": "../../infiles/com_orkut_sym.adj",
    "TASKPARTS_NUM_WORKERS": 64,
    "LD_PRELOAD": "/nix/store/ck10jnbska7d3im30v5mdbnlrgmhai0b-jemalloc-5.3.0/lib/libjemalloc.so",
    "exectime": 4.117,
    "usertime": 225.127,
    "systime": 34.866,
    "nvcsw": 188032,
    "nivcsw": 754,
    "maxrss": 8556544,
    "nsignals": 0,
    "nb_vertices": 21637296,
    "nb_steals": 3245477,
    "nb_suspends": 0,
    "nb_surplus_transitions": 0,
    "total_work_time": 92.097,
    "total_idle_time": 169.957,
    "total_suspend_time": 0.0,
    "total_time": 263.47,
    "utilization": 0.355,
    "timestamp": "23-11-06 20:39:55.275437"
  },
  {
    "benchmark": "suffix_tree",
    "filename": "../../infiles/wikisamp.xml",
    "TASKPARTS_NUM_WORKERS": 64,
    "LD_PRELOAD": "/nix/store/ck10jnbska7d3im30v5mdbnlrgmhai0b-jemalloc-5.3.0/lib/libjemalloc.so",
    "exectime": 9.324,
    "usertime": 503.266,
    "systime": 85.749,
    "nvcsw": 750705,
    "nivcsw": 2356,
    "maxrss": 9940992,
    "nsignals": 0,
    "nb_vertices": 356799898,
    "nb_steals": 475379,
    "nb_suspends": 0,
    "nb_surplus_transitions": 0,
    "total_work_time": 556.735,
    "total_idle_time": 39.36,
    "total_suspend_time": 0.0,
    "total_time": 596.76,
    "utilization": 0.934,
    "timestamp": "23-11-06 20:40:04.662406"
  },
  {
    "benchmark": "quickhull",
    "n": 134217728,
    "TASKPARTS_NUM_WORKERS": 64,
    "LD_PRELOAD": "/nix/store/ck10jnbska7d3im30v5mdbnlrgmhai0b-jemalloc-5.3.0/lib/libjemalloc.so",
    "exectime": 0.866,
    "usertime": 52.852,
    "systime": 2.022,
    "nvcsw": 2113,
    "nivcsw": 176,
    "maxrss": 2813952,
    "nsignals": 0,
    "nb_vertices": 5293485,
    "nb_steals": 45179,
    "nb_suspends": 0,
    "nb_surplus_transitions": 0,
    "total_work_time": 45.289,
    "total_idle_time": 9.865,
    "total_suspend_time": 0.0,
    "total_time": 55.397,
    "utilization": 0.822,
    "timestamp": "23-11-06 20:40:05.553697"
  },
  {
    "benchmark": "box_kdtree",
    "n": 1048576,
    "TASKPARTS_NUM_WORKERS": 64,
    "LD_PRELOAD": "/nix/store/ck10jnbska7d3im30v5mdbnlrgmhai0b-jemalloc-5.3.0/lib/libjemalloc.so",
    "exectime": 0.306,
    "usertime": 17.294,
    "systime": 1.665,
    "nvcsw": 6665,
    "nivcsw": 87,
    "maxrss": 790528,
    "nsignals": 0,
    "nb_vertices": 6200798,
    "nb_steals": 138205,
    "nb_suspends": 0,
    "nb_surplus_transitions": 0,
    "total_work_time": 17.141,
    "total_idle_time": 2.322,
    "total_suspend_time": 0.0,
    "total_time": 19.56,
    "utilization": 0.881,
    "timestamp": "23-11-06 20:40:05.893765"
  },
  {
    "benchmark": "le_list",
    "filename": "../../infiles/com_orkut_sym.adj",
    "TASKPARTS_NUM_WORKERS": 64,
    "LD_PRELOAD": "/nix/store/ck10jnbska7d3im30v5mdbnlrgmhai0b-jemalloc-5.3.0/lib/libjemalloc.so",
    "exectime": 2.989,
    "usertime": 140.444,
    "systime": 46.69,
    "nvcsw": 200471,
    "nivcsw": 592,
    "maxrss": 12205056,
    "nsignals": 0,
    "nb_vertices": 12244135,
    "nb_steals": 715921,
    "nb_suspends": 0,
    "nb_surplus_transitions": 0,
    "total_work_time": 146.96,
    "total_idle_time": 43.671,
    "total_suspend_time": 0.0,
    "total_time": 191.295,
    "utilization": 0.772,
    "timestamp": "23-11-06 20:40:08.999691"
  },
  {
    "benchmark": "kth_smallest",
    "n": 536870912,
    "TASKPARTS_NUM_WORKERS": 64,
    "LD_PRELOAD": "/nix/store/ck10jnbska7d3im30v5mdbnlrgmhai0b-jemalloc-5.3.0/lib/libjemalloc.so",
    "exectime": 0.863,
    "usertime": 47.724,
    "systime": 6.913,
    "nvcsw": 5307,
    "nivcsw": 91,
    "maxrss": 4913152,
    "nsignals": 0,
    "nb_vertices": 11126170,
    "nb_steals": 34245,
    "nb_suspends": 0,
    "nb_surplus_transitions": 0,
    "total_work_time": 39.056,
    "total_idle_time": 15.805,
    "total_suspend_time": 0.0,
    "total_time": 55.207,
    "utilization": 0.714,
    "timestamp": "23-11-06 20:40:09.888969"
  },
  {
    "benchmark": "huffman_tree",
    "n": 8388608,
    "TASKPARTS_NUM_WORKERS": 64,
    "LD_PRELOAD": "/nix/store/ck10jnbska7d3im30v5mdbnlrgmhai0b-jemalloc-5.3.0/lib/libjemalloc.so",
    "exectime": 0.518,
    "usertime": 30.077,
    "systime": 2.308,
    "nvcsw": 8296,
    "nivcsw": 88,
    "maxrss": 1257472,
    "nsignals": 0,
    "nb_vertices": 3405320,
    "nb_steals": 91243,
    "nb_suspends": 0,
    "nb_surplus_transitions": 0,
    "total_work_time": 29.084,
    "total_idle_time": 3.92,
    "total_suspend_time": 0.0,
    "total_time": 33.121,
    "utilization": 0.882,
    "timestamp": "23-11-06 20:40:10.438534"
  },
  {
    "benchmark": "2d_linear_program",
    "n": 67108864,
    "TASKPARTS_NUM_WORKERS": 64,
    "LD_PRELOAD": "/nix/store/ck10jnbska7d3im30v5mdbnlrgmhai0b-jemalloc-5.3.0/lib/libjemalloc.so",
    "exectime": 0.894,
    "usertime": 44.11,
    "systime": 12.73,
    "nvcsw": 2148,
    "nivcsw": 128,
    "maxrss": 3858432,
    "nsignals": 0,
    "nb_vertices": 1906804,
    "nb_steals": 51282,
    "nb_suspends": 0,
    "nb_surplus_transitions": 0,
    "total_work_time": 43.12,
    "total_idle_time": 13.824,
    "total_suspend_time": 0.0,
    "total_time": 57.243,
    "utilization": 0.759,
    "timestamp": "23-11-06 20:40:11.359894"
  },
  {
    "benchmark": "mcss",
    "n": 2147483648,
    "TASKPARTS_NUM_WORKERS": 64,
    "LD_PRELOAD": "/nix/store/ck10jnbska7d3im30v5mdbnlrgmhai0b-jemalloc-5.3.0/lib/libjemalloc.so",
    "exectime": 1.017,
    "usertime": 55.982,
    "systime": 8.657,
    "nvcsw": 3818,
    "nivcsw": 139,
    "maxrss": 8412160,
    "nsignals": 0,
    "nb_vertices": 141068,
    "nb_steals": 3925,
    "nb_suspends": 0,
    "nb_surplus_transitions": 0,
    "total_work_time": 40.396,
    "total_idle_time": 24.273,
    "total_suspend_time": 0.0,
    "total_time": 65.115,
    "utilization": 0.627,
    "timestamp": "23-11-06 20:40:12.404541"
  },
  {
    "benchmark": "nbody_fmm",
    "n": 65536,
    "TASKPARTS_NUM_WORKERS": 64,
    "LD_PRELOAD": "/nix/store/ck10jnbska7d3im30v5mdbnlrgmhai0b-jemalloc-5.3.0/lib/libjemalloc.so",
    "exectime": 0.078,
    "usertime": 4.37,
    "systime": 0.206,
    "nvcsw": 2925,
    "nivcsw": 38,
    "maxrss": 233472,
    "nsignals": 0,
    "nb_vertices": 37612,
    "nb_steals": 5756,
    "nb_suspends": 0,
    "nb_surplus_transitions": 0,
    "total_work_time": 3.344,
    "total_idle_time": 1.598,
    "total_suspend_time": 0.0,
    "total_time": 5.005,
    "utilization": 0.681,
    "timestamp": "23-11-06 20:40:12.520950"
  },
  {
    "benchmark": "spectral_separator",
    "n": 32768,
    "TASKPARTS_NUM_WORKERS": 64,
    "LD_PRELOAD": "/nix/store/ck10jnbska7d3im30v5mdbnlrgmhai0b-jemalloc-5.3.0/lib/libjemalloc.so",
    "exectime": 0.758,
    "usertime": 47.738,
    "systime": 0.26,
    "nvcsw": 2134,
    "nivcsw": 114,
    "maxrss": 168960,
    "nsignals": 0,
    "nb_vertices": 4820176,
    "nb_steals": 1276799,
    "nb_suspends": 0,
    "nb_surplus_transitions": 0,
    "total_work_time": 9.755,
    "total_idle_time": 38.416,
    "total_suspend_time": 0.0,
    "total_time": 48.49,
    "utilization": 0.208,
    "timestamp": "23-11-06 20:40:13.303912"
  },
  {
    "benchmark": "pagerank",
    "filename": "../../infiles/com_orkut_sym.adj",
    "TASKPARTS_NUM_WORKERS": 64,
    "LD_PRELOAD": "/nix/store/ck10jnbska7d3im30v5mdbnlrgmhai0b-jemalloc-5.3.0/lib/libjemalloc.so",
    "exectime": 2.503,
    "usertime": 120.366,
    "systime": 36.013,
    "nvcsw": 189753,
    "nivcsw": 618,
    "maxrss": 9923584,
    "nsignals": 0,
    "nb_vertices": 9958011,
    "nb_steals": 114040,
    "nb_suspends": 0,
    "nb_surplus_transitions": 0,
    "total_work_time": 134.033,
    "total_idle_time": 25.692,
    "total_suspend_time": 0.0,
    "total_time": 160.189,
    "utilization": 0.84,
    "timestamp": "23-11-06 20:40:15.879633"
  },
  {
    "benchmark": "cartesian_tree",
    "n": 268435456,
    "TASKPARTS_NUM_WORKERS": 64,
    "LD_PRELOAD": "/nix/store/ck10jnbska7d3im30v5mdbnlrgmhai0b-jemalloc-5.3.0/lib/libjemalloc.so",
    "exectime": 1.42,
    "usertime": 74.165,
    "systime": 16.21,
    "nvcsw": 5281,
    "nivcsw": 159,
    "maxrss": 6315008,
    "nsignals": 0,
    "nb_vertices": 42126019,
    "nb_steals": 13968,
    "nb_suspends": 0,
    "nb_surplus_transitions": 0,
    "total_work_time": 71.435,
    "total_idle_time": 19.065,
    "total_suspend_time": 0.0,
    "total_time": 90.888,
    "utilization": 0.79,
    "timestamp": "23-11-06 20:40:17.326736"
  },
  {
    "benchmark": "bellman_ford",
    "filename": "../../infiles/com_orkut_sym.adj",
    "TASKPARTS_NUM_WORKERS": 64,
    "LD_PRELOAD": "/nix/store/ck10jnbska7d3im30v5mdbnlrgmhai0b-jemalloc-5.3.0/lib/libjemalloc.so",
    "exectime": 1.93,
    "usertime": 86.241,
    "systime": 33.685,
    "nvcsw": 189542,
    "nivcsw": 515,
    "maxrss": 9928704,
    "nsignals": 0,
    "nb_vertices": 14210136,
    "nb_steals": 134415,
    "nb_suspends": 0,
    "nb_surplus_transitions": 0,
    "total_work_time": 98.138,
    "total_idle_time": 24.948,
    "total_suspend_time": 0.0,
    "total_time": 123.531,
    "utilization": 0.798,
    "timestamp": "23-11-06 20:40:19.323900"
  },
  {
    "benchmark": "linefit",
    "n": 1073741824,
    "TASKPARTS_NUM_WORKERS": 64,
    "LD_PRELOAD": "/nix/store/ck10jnbska7d3im30v5mdbnlrgmhai0b-jemalloc-5.3.0/lib/libjemalloc.so",
    "exectime": 2.868,
    "usertime": 174.163,
    "systime": 9.053,
    "nvcsw": 2176,
    "nivcsw": 327,
    "maxrss": 16795648,
    "nsignals": 0,
    "nb_vertices": 189098,
    "nb_steals": 7012,
    "nb_suspends": 0,
    "nb_surplus_transitions": 0,
    "total_work_time": 140.36,
    "total_idle_time": 42.475,
    "total_suspend_time": 0.0,
    "total_time": 183.556,
    "utilization": 0.769,
    "timestamp": "23-11-06 20:40:22.223307"
  },
  {
    "benchmark": "BFS",
    "filename": "../../infiles/com_orkut_sym.adj",
    "TASKPARTS_NUM_WORKERS": 64,
    "LD_PRELOAD": "/nix/store/ck10jnbska7d3im30v5mdbnlrgmhai0b-jemalloc-5.3.0/lib/libjemalloc.so",
    "exectime": 1.433,
    "usertime": 53.323,
    "systime": 34.925,
    "nvcsw": 186797,
    "nivcsw": 498,
    "maxrss": 8557568,
    "nsignals": 0,
    "nb_vertices": 4971186,
    "nb_steals": 63303,
    "nb_suspends": 0,
    "nb_surplus_transitions": 0,
    "total_work_time": 69.397,
    "total_idle_time": 21.891,
    "total_suspend_time": 0.0,
    "total_time": 91.707,
    "utilization": 0.761,
    "timestamp": "23-11-06 20:40:23.702096"
  },
  {
    "benchmark": "word_counts",
    "n": 5,
    "textfilename": "../../infiles/wikisamp.xml",
    "TASKPARTS_NUM_WORKERS": 64,
    "LD_PRELOAD": "/nix/store/ck10jnbska7d3im30v5mdbnlrgmhai0b-jemalloc-5.3.0/lib/libjemalloc.so",
    "exectime": 0.304,
    "usertime": 15.309,
    "systime": 3.211,
    "nvcsw": 6604,
    "nivcsw": 48,
    "maxrss": 801792,
    "nsignals": 0,
    "nb_vertices": 527263,
    "nb_steals": 24482,
    "nb_suspends": 0,
    "nb_surplus_transitions": 0,
    "total_work_time": 12.551,
    "total_idle_time": 6.778,
    "total_suspend_time": 0.0,
    "total_time": 19.484,
    "utilization": 0.652,
    "timestamp": "23-11-06 20:40:24.034377"
  },
  {
    "benchmark": "longest_common_prefix",
    "TASKPARTS_NUM_WORKERS": 64,
    "LD_PRELOAD": "/nix/store/ck10jnbska7d3im30v5mdbnlrgmhai0b-jemalloc-5.3.0/lib/libjemalloc.so",
    "exectime": 0.006,
    "usertime": 0.312,
    "systime": 0.006,
    "nvcsw": 157,
    "nivcsw": 5,
    "maxrss": 45056,
    "nsignals": 0,
    "nb_vertices": 129,
    "nb_steals": 63,
    "nb_suspends": 0,
    "nb_surplus_transitions": 0,
    "total_work_time": 0.128,
    "total_idle_time": 0.177,
    "total_suspend_time": 0.0,
    "total_time": 0.397,
    "utilization": 0.554,
    "timestamp": "23-11-06 20:40:24.063087"
  },
  {
    "benchmark": "set_cover",
    "filename": "../../infiles/com_orkut_sym.adj",
    "TASKPARTS_NUM_WORKERS": 64,
    "LD_PRELOAD": "/nix/store/ck10jnbska7d3im30v5mdbnlrgmhai0b-jemalloc-5.3.0/lib/libjemalloc.so",
    "exectime": 2.178,
    "usertime": 103.039,
    "systime": 33.054,
    "nvcsw": 188266,
    "nivcsw": 564,
    "maxrss": 8714240,
    "nsignals": 0,
    "nb_vertices": 16667413,
    "nb_steals": 755266,
    "nb_suspends": 0,
    "nb_surplus_transitions": 0,
    "total_work_time": 88.153,
    "total_idle_time": 50.644,
    "total_suspend_time": 0.0,
    "total_time": 139.388,
    "utilization": 0.637,
    "timestamp": "23-11-06 20:40:26.300867"
  },
  {
    "benchmark": "triangle_count",
    "filename": "../../infiles/com_orkut_sym.adj",
    "TASKPARTS_NUM_WORKERS": 64,
    "LD_PRELOAD": "/nix/store/ck10jnbska7d3im30v5mdbnlrgmhai0b-jemalloc-5.3.0/lib/libjemalloc.so",
    "exectime": 4.027,
    "usertime": 221.337,
    "systime": 33.063,
    "nvcsw": 187841,
    "nivcsw": 745,
    "maxrss": 8339456,
    "nsignals": 0,
    "nb_vertices": 7950965,
    "nb_steals": 30690,
    "nb_suspends": 0,
    "nb_surplus_transitions": 0,
    "total_work_time": 236.237,
    "total_idle_time": 21.096,
    "total_suspend_time": 0.0,
    "total_time": 257.742,
    "utilization": 0.918,
    "timestamp": "23-11-06 20:40:30.423373"
  },
  {
    "benchmark": "maximal_matching",
    "filename": "../../infiles/com_orkut_sym.adj",
    "TASKPARTS_NUM_WORKERS": 64,
    "LD_PRELOAD": "/nix/store/ck10jnbska7d3im30v5mdbnlrgmhai0b-jemalloc-5.3.0/lib/libjemalloc.so",
    "exectime": 1.614,
    "usertime": 72.086,
    "systime": 29.309,
    "nvcsw": 31524,
    "nivcsw": 160,
    "maxrss": 12300288,
    "nsignals": 0,
    "nb_vertices": 5740569,
    "nb_steals": 132468,
    "nb_suspends": 0,
    "nb_surplus_transitions": 0,
    "total_work_time": 68.0,
    "total_idle_time": 34.732,
    "total_suspend_time": 0.0,
    "total_time": 103.31,
    "utilization": 0.664,
    "timestamp": "23-11-06 20:40:32.089957"
  },
  {
    "benchmark": "quicksort",
    "n": 16777216,
    "TASKPARTS_NUM_WORKERS": 64,
    "LD_PRELOAD": "/nix/store/ck10jnbska7d3im30v5mdbnlrgmhai0b-jemalloc-5.3.0/lib/libjemalloc.so",
    "exectime": 0.339,
    "usertime": 17.648,
    "systime": 3.096,
    "nvcsw": 11838,
    "nivcsw": 49,
    "maxrss": 1939456,
    "nsignals": 0,
    "nb_vertices": 6381913,
    "nb_steals": 44061,
    "nb_suspends": 0,
    "nb_surplus_transitions": 0,
    "total_work_time": 15.931,
    "total_idle_time": 5.641,
    "total_suspend_time": 0.0,
    "total_time": 21.72,
    "utilization": 0.74,
    "timestamp": "23-11-06 20:40:32.462724"
  },
  {
    "benchmark": "low_diameter_decomposition",
    "filename": "../../infiles/com_orkut_sym.adj",
    "TASKPARTS_NUM_WORKERS": 64,
    "LD_PRELOAD": "/nix/store/ck10jnbska7d3im30v5mdbnlrgmhai0b-jemalloc-5.3.0/lib/libjemalloc.so",
    "exectime": 1.321,
    "usertime": 47.612,
    "systime": 33.53,
    "nvcsw": 187686,
    "nivcsw": 412,
    "maxrss": 8572928,
    "nsignals": 0,
    "nb_vertices": 2358278,
    "nb_steals": 80847,
    "nb_suspends": 0,
    "nb_surplus_transitions": 0,
    "total_work_time": 61.237,
    "total_idle_time": 22.875,
    "total_suspend_time": 0.0,
    "total_time": 84.521,
    "utilization": 0.729,
    "timestamp": "23-11-06 20:40:33.836268"
  },
  {
    "benchmark": "reduce",
    "n": 2147483648,
    "TASKPARTS_NUM_WORKERS": 64,
    "LD_PRELOAD": "/nix/store/ck10jnbska7d3im30v5mdbnlrgmhai0b-jemalloc-5.3.0/lib/libjemalloc.so",
    "exectime": 1.931,
    "usertime": 82.445,
    "systime": 40.459,
    "nvcsw": 6222,
    "nivcsw": 202,
    "maxrss": 16802816,
    "nsignals": 0,
    "nb_vertices": 6114977,
    "nb_steals": 6504,
    "nb_suspends": 0,
    "nb_surplus_transitions": 0,
    "total_work_time": 80.011,
    "total_idle_time": 42.832,
    "total_suspend_time": 0.0,
    "total_time": 123.583,
    "utilization": 0.653,
    "timestamp": "23-11-06 20:40:35.798620"
  },
  {
    "benchmark": "flatten",
    "n": 2147483648,
    "TASKPARTS_NUM_WORKERS": 64,
    "LD_PRELOAD": "/nix/store/ck10jnbska7d3im30v5mdbnlrgmhai0b-jemalloc-5.3.0/lib/libjemalloc.so",
    "exectime": 4.436,
    "usertime": 159.64,
    "systime": 120.888,
    "nvcsw": 66989,
    "nivcsw": 502,
    "maxrss": 50603008,
    "nsignals": 0,
    "nb_vertices": 35766641,
    "nb_steals": 13827,
    "nb_suspends": 0,
    "nb_surplus_transitions": 0,
    "total_work_time": 181.771,
    "total_idle_time": 100.449,
    "total_suspend_time": 0.0,
    "total_time": 283.874,
    "utilization": 0.646,
    "timestamp": "23-11-06 20:40:40.412243"
  },
  {
    "benchmark": "primes",
    "n": 1073741824,
    "TASKPARTS_NUM_WORKERS": 64,
    "LD_PRELOAD": "/nix/store/ck10jnbska7d3im30v5mdbnlrgmhai0b-jemalloc-5.3.0/lib/libjemalloc.so",
    "exectime": 0.653,
    "usertime": 36.033,
    "systime": 5.377,
    "nvcsw": 2916,
    "nivcsw": 73,
    "maxrss": 2982912,
    "nsignals": 0,
    "nb_vertices": 24918849,
    "nb_steals": 32102,
    "nb_suspends": 0,
    "nb_surplus_transitions": 0,
    "total_work_time": 31.442,
    "total_idle_time": 10.124,
    "total_suspend_time": 0.0,
    "total_time": 41.787,
    "utilization": 0.758,
    "timestamp": "23-11-06 20:40:41.090514"
  },
  {
    "benchmark": "rectangle_intersection",
    "n": 1048576,
    "TASKPARTS_NUM_WORKERS": 64,
    "LD_PRELOAD": "/nix/store/ck10jnbska7d3im30v5mdbnlrgmhai0b-jemalloc-5.3.0/lib/libjemalloc.so",
    "exectime": 0.379,
    "usertime": 22.163,
    "systime": 1.473,
    "nvcsw": 5976,
    "nivcsw": 97,
    "maxrss": 885760,
    "nsignals": 0,
    "nb_vertices": 6675614,
    "nb_steals": 147913,
    "nb_suspends": 0,
    "nb_surplus_transitions": 0,
    "total_work_time": 21.192,
    "total_idle_time": 2.956,
    "total_suspend_time": 0.0,
    "total_time": 24.247,
    "utilization": 0.878,
    "timestamp": "23-11-06 20:40:41.506516"
  },
  {
    "benchmark": "fast_fourier_transform",
    "n": 33554432,
    "TASKPARTS_NUM_WORKERS": 64,
    "LD_PRELOAD": "/nix/store/ck10jnbska7d3im30v5mdbnlrgmhai0b-jemalloc-5.3.0/lib/libjemalloc.so",
    "exectime": 1.386,
    "usertime": 83.868,
    "systime": 3.171,
    "nvcsw": 28818,
    "nivcsw": 134,
    "maxrss": 2809856,
    "nsignals": 0,
    "nb_vertices": 53343199,
    "nb_steals": 80977,
    "nb_suspends": 0,
    "nb_surplus_transitions": 0,
    "total_work_time": 81.723,
    "total_idle_time": 6.773,
    "total_suspend_time": 0.0,
    "total_time": 88.675,
    "utilization": 0.924,
    "timestamp": "23-11-06 20:40:42.941177"
  },
  {
    "benchmark": "BFS_ligra",
    "filename": "../../infiles/com_orkut_sym.adj",
    "TASKPARTS_NUM_WORKERS": 64,
    "LD_PRELOAD": "/nix/store/ck10jnbska7d3im30v5mdbnlrgmhai0b-jemalloc-5.3.0/lib/libjemalloc.so",
    "exectime": 1.247,
    "usertime": 42.518,
    "systime": 33.837,
    "nvcsw": 190115,
    "nivcsw": 414,
    "maxrss": 8538112,
    "nsignals": 0,
    "nb_vertices": 1868662,
    "nb_steals": 51707,
    "nb_suspends": 0,
    "nb_surplus_transitions": 0,
    "total_work_time": 57.801,
    "total_idle_time": 21.577,
    "total_suspend_time": 0.0,
    "total_time": 79.795,
    "utilization": 0.73,
    "timestamp": "23-11-06 20:40:44.234294"
  },
  {
    "benchmark": "bigint_add",
    "n": 8000000000,
    "TASKPARTS_NUM_WORKERS": 64,
    "LD_PRELOAD": "/nix/store/ck10jnbska7d3im30v5mdbnlrgmhai0b-jemalloc-5.3.0/lib/libjemalloc.so",
    "exectime": 0.479,
    "usertime": 22.601,
    "systime": 7.411,
    "nvcsw": 5575,
    "nivcsw": 57,
    "maxrss": 3932160,
    "nsignals": 0,
    "nb_vertices": 300727,
    "nb_steals": 8622,
    "nb_suspends": 0,
    "nb_surplus_transitions": 0,
    "total_work_time": 17.969,
    "total_idle_time": 12.453,
    "total_suspend_time": 0.0,
    "total_time": 30.68,
    "utilization": 0.594,
    "timestamp": "23-11-06 20:40:44.739880"
  },
  {
    "benchmark": "minimum_edit_distance",
    "n": 65536,
    "TASKPARTS_NUM_WORKERS": 64,
    "LD_PRELOAD": "/nix/store/ck10jnbska7d3im30v5mdbnlrgmhai0b-jemalloc-5.3.0/lib/libjemalloc.so",
    "exectime": 0.453,
    "usertime": 28.837,
    "systime": 0.021,
    "nvcsw": 358,
    "nivcsw": 89,
    "maxrss": 46080,
    "nsignals": 0,
    "nb_vertices": 3570694,
    "nb_steals": 897957,
    "nb_suspends": 0,
    "nb_surplus_transitions": 0,
    "total_work_time": 17.971,
    "total_idle_time": 10.861,
    "total_suspend_time": 0.0,
    "total_time": 28.967,
    "utilization": 0.625,
    "timestamp": "23-11-06 20:40:45.215794"
  },
  {
    "benchmark": "suffix_array",
    "filename": "../../infiles/chr22.dna",
    "TASKPARTS_NUM_WORKERS": 64,
    "LD_PRELOAD": "/nix/store/ck10jnbska7d3im30v5mdbnlrgmhai0b-jemalloc-5.3.0/lib/libjemalloc.so",
    "exectime": 2.16,
    "usertime": 133.373,
    "systime": 4.308,
    "nvcsw": 1483,
    "nivcsw": 252,
    "maxrss": 2313216,
    "nsignals": 0,
    "nb_vertices": 171436739,
    "nb_steals": 423461,
    "nb_suspends": 0,
    "nb_surplus_transitions": 0,
    "total_work_time": 124.802,
    "total_idle_time": 13.195,
    "total_suspend_time": 0.0,
    "total_time": 138.252,
    "utilization": 0.905,
    "timestamp": "23-11-06 20:40:47.403601"
  },
  {
    "benchmark": "oct_tree",
    "n": 8388608,
    "TASKPARTS_NUM_WORKERS": 64,
    "LD_PRELOAD": "/nix/store/ck10jnbska7d3im30v5mdbnlrgmhai0b-jemalloc-5.3.0/lib/libjemalloc.so",
    "exectime": 0.368,
    "usertime": 20.63,
    "systime": 2.087,
    "nvcsw": 8340,
    "nivcsw": 84,
    "maxrss": 874496,
    "nsignals": 0,
    "nb_vertices": 8260888,
    "nb_steals": 35363,
    "nb_suspends": 0,
    "nb_surplus_transitions": 0,
    "total_work_time": 20.804,
    "total_idle_time": 2.622,
    "total_suspend_time": 0.0,
    "total_time": 23.548,
    "utilization": 0.889,
    "timestamp": "23-11-06 20:40:47.797061"
  },
  {
    "benchmark": "knn",
    "n": 1048576,
    "TASKPARTS_NUM_WORKERS": 64,
    "LD_PRELOAD": "/nix/store/ck10jnbska7d3im30v5mdbnlrgmhai0b-jemalloc-5.3.0/lib/libjemalloc.so",
    "exectime": 0.41,
    "usertime": 22.892,
    "systime": 2.61,
    "nvcsw": 3574,
    "nivcsw": 65,
    "maxrss": 898048,
    "nsignals": 0,
    "nb_vertices": 2735186,
    "nb_steals": 34903,
    "nb_suspends": 0,
    "nb_surplus_transitions": 0,
    "total_work_time": 23.205,
    "total_idle_time": 2.926,
    "total_suspend_time": 0.0,
    "total_time": 26.229,
    "utilization": 0.888,
    "timestamp": "23-11-06 20:40:48.233542"
  },
  {
    "benchmark": "lasso_regression",
    "filename": "../../infiles/finance1000.lasso.txt",
    "TASKPARTS_NUM_WORKERS": 64,
    "LD_PRELOAD": "/nix/store/ck10jnbska7d3im30v5mdbnlrgmhai0b-jemalloc-5.3.0/lib/libjemalloc.so",
    "exectime": 1.612,
    "usertime": 100.255,
    "systime": 2.283,
    "nvcsw": 9799,
    "nivcsw": 218,
    "maxrss": 689152,
    "nsignals": 0,
    "nb_vertices": 3728869,
    "nb_steals": 273624,
    "nb_suspends": 0,
    "nb_surplus_transitions": 0,
    "total_work_time": 86.523,
    "total_idle_time": 16.449,
    "total_suspend_time": 0.0,
    "total_time": 103.148,
    "utilization": 0.841,
    "timestamp": "23-11-06 20:40:49.870374"
  },
  {
    "benchmark": "betweenness_centrality",
    "filename": "../../infiles/com_orkut_sym.adj",
    "TASKPARTS_NUM_WORKERS": 64,
    "LD_PRELOAD": "/nix/store/ck10jnbska7d3im30v5mdbnlrgmhai0b-jemalloc-5.3.0/lib/libjemalloc.so",
    "exectime": 1.399,
    "usertime": 51.64,
    "systime": 34.52,
    "nvcsw": 186696,
    "nivcsw": 413,
    "maxrss": 8548352,
    "nsignals": 0,
    "nb_vertices": 2403501,
    "nb_steals": 61756,
    "nb_suspends": 0,
    "nb_surplus_transitions": 0,
    "total_work_time": 66.883,
    "total_idle_time": 22.234,
    "total_suspend_time": 0.0,
    "total_time": 89.509,
    "utilization": 0.752,
    "timestamp": "23-11-06 20:40:51.317733"
  },
  {
    "benchmark": "mergesort",
    "n": 33554432,
    "TASKPARTS_NUM_WORKERS": 64,
    "LD_PRELOAD": "/nix/store/ck10jnbska7d3im30v5mdbnlrgmhai0b-jemalloc-5.3.0/lib/libjemalloc.so",
    "exectime": 0.515,
    "usertime": 30.911,
    "systime": 1.297,
    "nvcsw": 7312,
    "nivcsw": 73,
    "maxrss": 808960,
    "nsignals": 0,
    "nb_vertices": 15071907,
    "nb_steals": 40781,
    "nb_suspends": 0,
    "nb_surplus_transitions": 0,
    "total_work_time": 29.781,
    "total_idle_time": 3.071,
    "total_suspend_time": 0.0,
    "total_time": 32.965,
    "utilization": 0.907,
    "timestamp": "23-11-06 20:40:51.858115"
  },
  {
    "benchmark": "radix_tree",
    "filename": "../../infiles/wikisamp.xml",
    "TASKPARTS_NUM_WORKERS": 64,
    "LD_PRELOAD": "/nix/store/ck10jnbska7d3im30v5mdbnlrgmhai0b-jemalloc-5.3.0/lib/libjemalloc.so",
    "exectime": 0.177,
    "usertime": 8.521,
    "systime": 2.052,
    "nvcsw": 9595,
    "nivcsw": 58,
    "maxrss": 814080,
    "nsignals": 0,
    "nb_vertices": 769845,
    "nb_steals": 36754,
    "nb_suspends": 0,
    "nb_surplus_transitions": 0,
    "total_work_time": 6.186,
    "total_idle_time": 4.997,
    "total_suspend_time": 0.0,
    "total_time": 11.316,
    "utilization": 0.558,
    "timestamp": "23-11-06 20:40:52.062855"
  },
  {
    "benchmark": "3d_range",
    "n": 2097152,
    "TASKPARTS_NUM_WORKERS": 64,
    "LD_PRELOAD": "/nix/store/ck10jnbska7d3im30v5mdbnlrgmhai0b-jemalloc-5.3.0/lib/libjemalloc.so",
    "exectime": 0.312,
    "usertime": 17.876,
    "systime": 1.408,
    "nvcsw": 4290,
    "nivcsw": 84,
    "maxrss": 479232,
    "nsignals": 0,
    "nb_vertices": 3851613,
    "nb_steals": 34517,
    "nb_suspends": 0,
    "nb_surplus_transitions": 0,
    "total_work_time": 18.703,
    "total_idle_time": 1.219,
    "total_suspend_time": 0.0,
    "total_time": 19.999,
    "utilization": 0.939,
    "timestamp": "23-11-06 20:40:52.400483"
  },
  {
    "benchmark": "graph_color",
    "filename": "../../infiles/com_orkut_sym.adj",
    "TASKPARTS_NUM_WORKERS": 64,
    "LD_PRELOAD": "/nix/store/ck10jnbska7d3im30v5mdbnlrgmhai0b-jemalloc-5.3.0/lib/libjemalloc.so",
    "exectime": 2.311,
    "usertime": 110.894,
    "systime": 33.715,
    "nvcsw": 186037,
    "nivcsw": 532,
    "maxrss": 8373248,
    "nsignals": 0,
    "nb_vertices": 25329078,
    "nb_steals": 1672285,
    "nb_suspends": 0,
    "nb_surplus_transitions": 0,
    "total_work_time": 91.85,
    "total_idle_time": 55.436,
    "total_suspend_time": 0.0,
    "total_time": 147.91,
    "utilization": 0.625,
    "timestamp": "23-11-06 20:40:54.759306"
  },
  {
    "benchmark": "ray_trace",
    "n": 262144,
    "TASKPARTS_NUM_WORKERS": 64,
    "LD_PRELOAD": "/nix/store/ck10jnbska7d3im30v5mdbnlrgmhai0b-jemalloc-5.3.0/lib/libjemalloc.so",
    "exectime": 0.624,
    "usertime": 38.478,
    "systime": 1.008,
    "nvcsw": 6036,
    "nivcsw": 97,
    "maxrss": 458752,
    "nsignals": 0,
    "nb_vertices": 2821789,
    "nb_steals": 189709,
    "nb_suspends": 0,
    "nb_surplus_transitions": 0,
    "total_work_time": 37.515,
    "total_idle_time": 2.343,
    "total_suspend_time": 0.0,
    "total_time": 39.946,
    "utilization": 0.941,
    "timestamp": "23-11-06 20:40:55.415577"
  },
  {
    "benchmark": "knuth_morris_pratt",
    "search_string": "xxx",
    "textfilename": "../../infiles/wikisamp.xml",
    "TASKPARTS_NUM_WORKERS": 64,
    "LD_PRELOAD": "/nix/store/ck10jnbska7d3im30v5mdbnlrgmhai0b-jemalloc-5.3.0/lib/libjemalloc.so",
    "exectime": 0.074,
    "usertime": 4.327,
    "systime": 0.066,
    "nvcsw": 419,
    "nivcsw": 44,
    "maxrss": 148480,
    "nsignals": 0,
    "nb_vertices": 118700,
    "nb_steals": 6411,
    "nb_suspends": 0,
    "nb_surplus_transitions": 0,
    "total_work_time": 1.024,
    "total_idle_time": 3.605,
    "total_suspend_time": 0.0,
    "total_time": 4.767,
    "utilization": 0.244,
    "timestamp": "23-11-06 20:40:55.515153"
  },
  {
    "benchmark": "find_if",
    "TASKPARTS_NUM_WORKERS": 64,
    "LD_PRELOAD": "/nix/store/ck10jnbska7d3im30v5mdbnlrgmhai0b-jemalloc-5.3.0/lib/libjemalloc.so",
    "exectime": 0.006,
    "usertime": 0.305,
    "systime": 0.009,
    "nvcsw": 126,
    "nivcsw": 7,
    "maxrss": 45056,
    "nsignals": 0,
    "nb_vertices": 129,
    "nb_steals": 63,
    "nb_suspends": 0,
    "nb_surplus_transitions": 0,
    "total_work_time": 0.126,
    "total_idle_time": 0.175,
    "total_suspend_time": 0.0,
    "total_time": 0.392,
    "utilization": 0.555,
    "timestamp": "23-11-06 20:40:55.543779"
  },
  {
    "benchmark": "maximal_independent_set",
    "filename": "../../infiles/com_orkut_sym.adj",
    "TASKPARTS_NUM_WORKERS": 64,
    "LD_PRELOAD": "/nix/store/ck10jnbska7d3im30v5mdbnlrgmhai0b-jemalloc-5.3.0/lib/libjemalloc.so",
    "exectime": 1.319,
    "usertime": 45.659,
    "systime": 35.37,
    "nvcsw": 185957,
    "nivcsw": 522,
    "maxrss": 8302592,
    "nsignals": 0,
    "nb_vertices": 4164345,
    "nb_steals": 197129,
    "nb_suspends": 0,
    "nb_surplus_transitions": 0,
    "total_work_time": 60.347,
    "total_idle_time": 23.672,
    "total_suspend_time": 0.0,
    "total_time": 84.446,
    "utilization": 0.72,
    "timestamp": "23-11-06 20:40:56.913239"
  },
  {
    "benchmark": "filter",
    "n": 2147483648,
    "TASKPARTS_NUM_WORKERS": 64,
    "LD_PRELOAD": "/nix/store/ck10jnbska7d3im30v5mdbnlrgmhai0b-jemalloc-5.3.0/lib/libjemalloc.so",
    "exectime": 1.944,
    "usertime": 80.799,
    "systime": 43.111,
    "nvcsw": 2891,
    "nivcsw": 177,
    "maxrss": 18917376,
    "nsignals": 0,
    "nb_vertices": 45936759,
    "nb_steals": 27110,
    "nb_suspends": 0,
    "nb_surplus_transitions": 0,
    "total_work_time": 78.908,
    "total_idle_time": 44.742,
    "total_suspend_time": 0.0,
    "total_time": 124.423,
    "utilization": 0.64,
    "timestamp": "23-11-06 20:40:58.890658"
  },
  {
    "benchmark": "range_min",
    "n": 33554432,
    "TASKPARTS_NUM_WORKERS": 64,
    "LD_PRELOAD": "/nix/store/ck10jnbska7d3im30v5mdbnlrgmhai0b-jemalloc-5.3.0/lib/libjemalloc.so",
    "exectime": 0.398,
    "usertime": 23.877,
    "systime": 0.833,
    "nvcsw": 6427,
    "nivcsw": 51,
    "maxrss": 894976,
    "nsignals": 0,
    "nb_vertices": 1365118,
    "nb_steals": 38803,
    "nb_suspends": 0,
    "nb_surplus_transitions": 0,
    "total_work_time": 21.597,
    "total_idle_time": 3.721,
    "total_suspend_time": 0.0,
    "total_time": 25.457,
    "utilization": 0.854,
    "timestamp": "23-11-06 20:40:59.313069"
  },
  {
    "benchmark": "longest_repeated_substring",
    "filename": "../../infiles/wikisamp.xml",
    "TASKPARTS_NUM_WORKERS": 64,
    "LD_PRELOAD": "/nix/store/ck10jnbska7d3im30v5mdbnlrgmhai0b-jemalloc-5.3.0/lib/libjemalloc.so",
    "exectime": 4.988,
    "usertime": 307.016,
    "systime": 11.662,
    "nvcsw": 1744,
    "nivcsw": 517,
    "maxrss": 6179840,
    "nsignals": 0,
    "nb_vertices": 268496806,
    "nb_steals": 277096,
    "nb_suspends": 0,
    "nb_surplus_transitions": 0,
    "total_work_time": 294.793,
    "total_idle_time": 24.013,
    "total_suspend_time": 0.0,
    "total_time": 319.26,
    "utilization": 0.925,
    "timestamp": "23-11-06 20:41:04.334806"
  },
  {
    "benchmark": "decision_tree_c45",
    "filename": "../../infiles/kddcup.data.test",
    "TASKPARTS_NUM_WORKERS": 64,
    "LD_PRELOAD": "/nix/store/ck10jnbska7d3im30v5mdbnlrgmhai0b-jemalloc-5.3.0/lib/libjemalloc.so",
    "exectime": 0.343,
    "usertime": 13.782,
    "systime": 6.456,
    "nvcsw": 101025,
    "nivcsw": 262,
    "maxrss": 752640,
    "nsignals": 0,
    "nb_vertices": 2013529,
    "nb_steals": 72320,
    "nb_suspends": 0,
    "nb_surplus_transitions": 0,
    "total_work_time": 20.392,
    "total_idle_time": 1.492,
    "total_suspend_time": 0.0,
    "total_time": 21.96,
    "utilization": 0.932,
    "timestamp": "23-11-06 20:41:04.720998"
  },
  {
    "benchmark": "knuth_shuffle",
    "n": 33554432,
    "TASKPARTS_NUM_WORKERS": 64,
    "LD_PRELOAD": "/nix/store/ck10jnbska7d3im30v5mdbnlrgmhai0b-jemalloc-5.3.0/lib/libjemalloc.so",
    "exectime": 0.761,
    "usertime": 44.984,
    "systime": 2.886,
    "nvcsw": 6579,
    "nivcsw": 79,
    "maxrss": 1220608,
    "nsignals": 0,
    "nb_vertices": 7932517,
    "nb_steals": 299443,
    "nb_suspends": 0,
    "nb_surplus_transitions": 0,
    "total_work_time": 41.55,
    "total_idle_time": 6.99,
    "total_suspend_time": 0.0,
    "total_time": 48.695,
    "utilization": 0.856,
    "timestamp": "23-11-06 20:41:05.507540"
  },
  {
    "benchmark": "cycle_count",
    "n": 16777216,
    "TASKPARTS_NUM_WORKERS": 64,
    "LD_PRELOAD": "/nix/store/ck10jnbska7d3im30v5mdbnlrgmhai0b-jemalloc-5.3.0/lib/libjemalloc.so",
    "exectime": 0.343,
    "usertime": 17.94,
    "systime": 3.311,
    "nvcsw": 4033,
    "nivcsw": 84,
    "maxrss": 913408,
    "nsignals": 0,
    "nb_vertices": 840416,
    "nb_steals": 12835,
    "nb_suspends": 0,
    "nb_surplus_transitions": 0,
    "total_work_time": 18.178,
    "total_idle_time": 3.666,
    "total_suspend_time": 0.0,
    "total_time": 21.959,
    "utilization": 0.833,
    "timestamp": "23-11-06 20:41:05.874791"
  },
  {
    "benchmark": "hash_map",
    "n": 33554432,
    "TASKPARTS_NUM_WORKERS": 64,
    "LD_PRELOAD": "/nix/store/ck10jnbska7d3im30v5mdbnlrgmhai0b-jemalloc-5.3.0/lib/libjemalloc.so",
    "exectime": 0.827,
    "usertime": 47.721,
    "systime": 4.496,
    "nvcsw": 5441,
    "nivcsw": 127,
    "maxrss": 1728512,
    "nsignals": 0,
    "nb_vertices": 399313,
    "nb_steals": 11011,
    "nb_suspends": 0,
    "nb_surplus_transitions": 0,
    "total_work_time": 46.593,
    "total_idle_time": 6.158,
    "total_suspend_time": 0.0,
    "total_time": 52.906,
    "utilization": 0.884,
    "timestamp": "23-11-06 20:41:06.727913"
  }
]